Metadata-Version: 2.1
Name: aiosqlite-black
Version: 0.21.0
Summary: asyncio bridge to the standard sqlite3 module
Author-email: bsxcs + Amethyst Reese <amy@n7.gg>
Requires-Python: >=3.8
Classifier: Development Status :: 5 - Production/Stable
Classifier: Framework :: AsyncIO
Classifier: Intended Audience :: Developers
Classifier: License :: OSI Approved :: MIT License
Classifier: Topic :: Software Development :: Libraries
Requires-Dist: typing_extensions >= 4.0
Requires-Dist: attribution==1.7.0 ; extra == "dev"
Requires-Dist: black==24.2.0 ; extra == "dev"
Requires-Dist: coverage[toml]==7.4.1 ; extra == "dev"
Requires-Dist: flake8==7.0.0 ; extra == "dev"
Requires-Dist: flake8-bugbear==24.2.6 ; extra == "dev"
Requires-Dist: flit==3.9.0 ; extra == "dev"
Requires-Dist: mypy==1.8.0 ; extra == "dev"
Requires-Dist: ufmt==2.3.0 ; extra == "dev"
Requires-Dist: usort==1.0.8.post1 ; extra == "dev"
Requires-Dist: sphinx==7.2.6 ; extra == "docs"
Requires-Dist: sphinx-mdinclude==0.5.3 ; extra == "docs"
Project-URL: Documentation, https://aiosqlite.omnilib.dev
Project-URL: Github, https://github.com/eyMarv/aiosqlite-black
Provides-Extra: dev
Provides-Extra: docs
